{
  "generated": "2026-07-21 10:57:23",
  "generated_utc": "2026-07-21T10:57:23Z",
  "generated_beijing": "2026-07-21 18:57:23 Asia/Shanghai",
  "sources_total": 29,
  "sources_fetched_ok": 29,
  "upstream_fetch_bytes": 7471690,
  "resource_budgets": {
    "max_candidates_per_source": 50000,
    "max_total_candidates": 250000,
    "max_unique_urls": 100000,
    "max_source_bytes": 30000000,
    "max_total_fetch_bytes": 180000000,
    "max_pending_futures": 1024
  },
  "parsed_candidates": 34968,
  "unique_candidates": 29624,
  "unique_name_url_candidates": 30523,
  "checked_candidates": 29624,
  "broad_media_probe_checked": 29624,
  "broad_checked_all_unique": true,
  "strict_video_checked_unique": 2807,
  "strict_progress_checked_unique": 339,
  "checked_all_unique": true,
  "first_pass_validation": {
    "require_video_track": false,
    "public_network_policy_enabled": true,
    "hls_segment_checks": 2,
    "core_hls_segment_checks": 3
  },
  "playable_channel_names": 10319,
  "playable_unique_urls": 13208,
  "playable_name_url_lines": 13730,
  "playable_urls_found": 13730,
  "all_playable_lines": 13730,
  "pre_curated_published_lines": 12106,
  "primary_published_lines": 2661,
  "pre_recheck_curated_lines": 2778,
  "pre_recheck_curated_channel_names": 1720,
  "pre_recheck_curated_groups": {
    "央视频道": 131,
    "卫视频道": 198,
    "地方频道": 864,
    "影视剧场": 172,
    "少儿动漫": 25,
    "体育纪实": 64,
    "音乐综艺": 35,
    "生活休闲": 96,
    "综合娱乐": 900,
    "港澳台频道": 73,
    "海外华语频道": 220
  },
  "pre_recheck_curated_sources": {
    "zbds_iptv4_txt": 436,
    "guovin_ipv4": 213,
    "iyouhun_zb": 343,
    "migu_interface": 35,
    "suxuang_ipv4": 143,
    "iptv_org_all": 12,
    "epg_cn": 452,
    "guovin_all": 354,
    "suxuang_ipv6": 6,
    "guovin_ipv6": 2,
    "bigbiggrandg_gather": 431,
    "vamoschuck_m3u": 10,
    "mursor_yy": 310,
    "kimentanm_aptv": 3,
    "epg_tw": 18,
    "yang_gather": 2,
    "epg_mo": 6,
    "free_tv_world": 1,
    "iptv_org_tw": 1
  },
  "pre_recheck_per_group_unique_names": {
    "央视频道": 27,
    "卫视频道": 45,
    "地方频道": 359,
    "影视剧场": 130,
    "少儿动漫": 14,
    "体育纪实": 43,
    "音乐综艺": 31,
    "生活休闲": 62,
    "综合娱乐": 740,
    "港澳台频道": 59,
    "海外华语频道": 210
  },
  "stability_history_loaded": true,
  "stability_history_urls": 4827,
  "home_priority": {
    "enabled": true,
    "ok_urls": 0,
    "failed_urls": 0,
    "bonus": -120,
    "penalty": 180
  },
  "curated_generated": true,
  "curated_source_map_available": true,
  "curated_source_map_generated": true,
  "curated_source_map_artifact_only": true,
  "curated_candidate_pool_generated": true,
  "curated_candidate_pool_artifact_only": true,
  "curated_published_lines": 2661,
  "curated_channel_names": 1633,
  "curated_groups": {
    "央视频道": 129,
    "卫视频道": 182,
    "地方频道": 827,
    "影视剧场": 172,
    "少儿动漫": 25,
    "体育纪实": 64,
    "音乐综艺": 24,
    "生活休闲": 89,
    "综合娱乐": 868,
    "港澳台频道": 64,
    "海外华语频道": 217
  },
  "curated_sources": {
    "zbds_iptv4_txt": 399,
    "guovin_ipv4": 212,
    "iyouhun_zb": 344,
    "migu_interface": 35,
    "suxuang_ipv4": 140,
    "iptv_org_all": 8,
    "epg_cn": 439,
    "guovin_ipv6": 2,
    "guovin_all": 343,
    "vamoschuck_m3u": 10,
    "mursor_yy": 305,
    "bigbiggrandg_gather": 388,
    "kimentanm_aptv": 3,
    "epg_tw": 18,
    "yang_gather": 2,
    "epg_mo": 6,
    "free_tv_world": 1,
    "suxuang_ipv6": 5,
    "iptv_org_tw": 1
  },
  "per_group_unique_names": {
    "央视频道": 27,
    "卫视频道": 45,
    "地方频道": 359,
    "影视剧场": 130,
    "少儿动漫": 14,
    "体育纪实": 43,
    "音乐综艺": 31,
    "生活休闲": 62,
    "综合娱乐": 740,
    "港澳台频道": 59,
    "海外华语频道": 210
  },
  "alias_resolution": {
    "conflicting_urls_excluded": 127,
    "conflicting_alias_rows_excluded": 270,
    "report_file": "alias-conflict-report.md",
    "candidate_pool_file": "curated-candidate-pool.csv"
  },
  "quality_limits_applied": {
    "config_file": "config/quality.json",
    "channel_limit_trimmed_rows": 1707,
    "channel_limit_trimmed_by_group": {
      "地方频道": 815,
      "海外华语频道": 27,
      "少儿动漫": 18,
      "综合娱乐": 335,
      "影视剧场": 69,
      "生活休闲": 67,
      "港澳台频道": 20,
      "体育纪实": 77,
      "卫视频道": 57,
      "音乐综艺": 15,
      "央视频道": 207
    },
    "group_limit_trimmed_counts": {
      "综合娱乐": 14,
      "海外华语频道": 151
    },
    "strict_filter_dropped_rows": 494,
    "drop_counts": {
      "unwanted_overseas_english": 6988,
      "strict_quality_filter": 494,
      "unstable_or_wrong_alias": 822,
      "foreign_channel": 421,
      "cgtn_url": 26,
      "invalid_name_or_url": 3,
      "ambiguous_url_identity": 270
    },
    "top_strict_drop_reasons": {
      "token:Geo-blocked": 263,
      "audio-only:radio": 126,
      "token:Astro": 23,
      "regex:(^|[^A-Za-z])(Animal[_ ]?Planet|Discovery(Asia)?|FashionTV|Foodnetwork|HGTV|History|NatGeo(_?Wild)?|CartoonNetwork|BabyTV|Animax|CBeebies|KidsTV|CampSpoopy)([^A-Za-z]|$)": 19,
      "token:Discovery": 9,
      "token:FashionTV": 7,
      "token:NatGeo": 6,
      "token:Ocko": 5,
      "token:GOODTV": 5,
      "token:HGTV": 2,
      "token:CityFM": 2,
      "token:CampSpoopy": 2,
      "token:Foodnetwork": 2,
      "token:AnimalPlanet": 2,
      "token:澳門MACAU": 2,
      "token:|BabyTV": 2,
      "token:BreadTV": 1,
      "token:SimonAmstell": 1,
      "token:Storm憋了一年大招": 1,
      "token:DJSoda": 1
    },
    "group_max_rows": {
      "影视剧场": 180,
      "少儿动漫": 40,
      "体育纪实": 90,
      "音乐综艺": 80,
      "生活休闲": 180,
      "综合娱乐": 900,
      "港澳台频道": 90,
      "海外华语频道": 220
    },
    "channel_limits": {
      "default_max_urls_per_name": 4,
      "core_max_urls_per_name": 6,
      "cctv_max_urls_per_name": 6,
      "satellite_max_urls_per_name": 5,
      "local_max_urls_per_name": 5,
      "movie_max_urls_per_name": 3,
      "kids_max_urls_per_name": 3,
      "sport_doc_max_urls_per_name": 3,
      "music_show_max_urls_per_name": 3,
      "life_max_urls_per_name": 3,
      "entertainment_max_urls_per_name": 3,
      "hk_max_urls_per_name": 2,
      "oversea_max_urls_per_name": 2
    }
  },
  "final_primary_file": "live-curated.txt",
  "final_primary_published_lines": 2661,
  "curated_group_sources": {
    "央视频道|zbds_iptv4_txt": 30,
    "央视频道|guovin_ipv4": 56,
    "央视频道|iyouhun_zb": 6,
    "央视频道|migu_interface": 3,
    "央视频道|suxuang_ipv4": 2,
    "央视频道|iptv_org_all": 4,
    "央视频道|epg_cn": 28,
    "卫视频道|guovin_ipv4": 106,
    "卫视频道|suxuang_ipv4": 19,
    "卫视频道|zbds_iptv4_txt": 45,
    "卫视频道|iyouhun_zb": 8,
    "卫视频道|migu_interface": 1,
    "卫视频道|iptv_org_all": 1,
    "卫视频道|guovin_ipv6": 2,
    "地方频道|zbds_iptv4_txt": 224,
    "地方频道|epg_cn": 142,
    "地方频道|iyouhun_zb": 160,
    "地方频道|guovin_all": 246,
    "地方频道|migu_interface": 11,
    "地方频道|vamoschuck_m3u": 9,
    "地方频道|mursor_yy": 1,
    "地方频道|suxuang_ipv4": 23,
    "地方频道|guovin_ipv4": 11,
    "影视剧场|mursor_yy": 45,
    "影视剧场|guovin_ipv4": 14,
    "影视剧场|zbds_iptv4_txt": 23,
    "影视剧场|bigbiggrandg_gather": 5,
    "影视剧场|guovin_all": 31,
    "影视剧场|suxuang_ipv4": 28,
    "影视剧场|iyouhun_zb": 23,
    "影视剧场|vamoschuck_m3u": 1,
    "影视剧场|migu_interface": 2,
    "少儿动漫|guovin_all": 8,
    "少儿动漫|epg_cn": 9,
    "少儿动漫|iyouhun_zb": 2,
    "少儿动漫|mursor_yy": 6,
    "体育纪实|epg_cn": 3,
    "体育纪实|guovin_ipv4": 10,
    "体育纪实|zbds_iptv4_txt": 30,
    "体育纪实|iyouhun_zb": 16,
    "体育纪实|guovin_all": 2,
    "体育纪实|mursor_yy": 3,
    "音乐综艺|mursor_yy": 14,
    "音乐综艺|bigbiggrandg_gather": 2,
    "音乐综艺|kimentanm_aptv": 3,
    "音乐综艺|epg_cn": 1,
    "音乐综艺|iyouhun_zb": 1,
    "音乐综艺|guovin_ipv4": 3,
    "生活休闲|iyouhun_zb": 33,
    "生活休闲|mursor_yy": 5,
    "生活休闲|bigbiggrandg_gather": 6,
    "生活休闲|epg_cn": 15,
    "生活休闲|guovin_all": 26,
    "生活休闲|guovin_ipv4": 3,
    "生活休闲|iptv_org_all": 1,
    "综合娱乐|iyouhun_zb": 77,
    "综合娱乐|mursor_yy": 16,
    "综合娱乐|epg_cn": 224,
    "综合娱乐|zbds_iptv4_txt": 46,
    "综合娱乐|bigbiggrandg_gather": 371,
    "综合娱乐|guovin_all": 23,
    "综合娱乐|suxuang_ipv4": 61,
    "综合娱乐|migu_interface": 18,
    "综合娱乐|epg_tw": 17,
    "综合娱乐|yang_gather": 2,
    "综合娱乐|guovin_ipv4": 7,
    "综合娱乐|epg_mo": 6,
    "港澳台频道|suxuang_ipv4": 7,
    "港澳台频道|epg_cn": 17,
    "港澳台频道|free_tv_world": 1,
    "港澳台频道|suxuang_ipv6": 5,
    "港澳台频道|epg_tw": 1,
    "港澳台频道|guovin_ipv4": 2,
    "港澳台频道|iyouhun_zb": 18,
    "港澳台频道|bigbiggrandg_gather": 4,
    "港澳台频道|guovin_all": 7,
    "港澳台频道|mursor_yy": 1,
    "港澳台频道|zbds_iptv4_txt": 1,
    "海外华语频道|mursor_yy": 214,
    "海外华语频道|iptv_org_tw": 1,
    "海外华语频道|iptv_org_all": 2
  },
  "final_publish_report_file": "final-publish-report.md",
  "family_playlist": {
    "enabled": true,
    "txt_files": [
      "ku9-family.txt",
      "live-family.txt"
    ],
    "m3u_file": "family.m3u",
    "lines": 1169,
    "unique_names": 891,
    "unique_urls": 1169,
    "groups": {
      "央视频道": 91,
      "卫视频道": 144,
      "地方频道": 320,
      "影视剧场": 90,
      "少儿动漫": 14,
      "体育纪实": 43,
      "音乐综艺": 20,
      "生活休闲": 57,
      "综合娱乐": 260,
      "港澳台频道": 50,
      "海外华语频道": 80
    },
    "min_lines": 700,
    "max_lines": 1400
  },
  "stability": {
    "enabled": true,
    "history_file": "stability-history.tsv",
    "tracked_urls_before": 4827,
    "tracked_urls_after": 4846,
    "max_entries": 5000,
    "new_urls": 19,
    "updated_urls": 2807,
    "ok_updates": 2661,
    "fail_updates": 146,
    "trimmed_urls": 0,
    "last_updated_beijing": "2026-07-21T19:04:29+08:00",
    "current_adjustment_min": -90,
    "current_adjustment_max": 140
  },
  "published_recheck": {
    "enabled": true,
    "checked_unique_urls": 2807,
    "initial_checked_unique_urls": 2778,
    "before_rows": 2778,
    "after_rows": 2661,
    "removed_rows": 117,
    "first_pass_failed_unique_urls": 252,
    "slow_retry_attempted_unique_urls": 252,
    "slow_retry_recovered_unique_urls": 113,
    "post_retry_failed_unique_urls": 139,
    "initial_failed_unique_urls": 139,
    "refill_failed_unique_urls": 7,
    "failed_unique_urls": 146,
    "core_progress_required": true,
    "require_video_track": true,
    "video_track_verified_unique_urls": 2661,
    "audio_only_rejected_unique_urls": 74,
    "unknown_track_rejected_unique_urls": 17,
    "public_network_policy_enabled": true,
    "refill": {
      "enabled": true,
      "channels_with_deficit": 122,
      "target_rows": 139,
      "attempted_unique_urls": 29,
      "playable_unique_urls": 22,
      "refilled_rows": 22,
      "unresolved_rows": 117,
      "initial_retry": {
        "configured_attempts": 1,
        "timeout_seconds": 14,
        "workers": 16,
        "first_pass_failed_unique_urls": 252,
        "initial_failed_unique_urls": 252,
        "attempted_unique_urls": 252,
        "recovered_unique_urls": 113,
        "still_failed_unique_urls": 139
      }
    },
    "slow_retry": {
      "configured_attempts": 1,
      "timeout_seconds": 14,
      "workers": 16,
      "first_pass_failed_unique_urls": 252,
      "initial_failed_unique_urls": 252,
      "attempted_unique_urls": 252,
      "recovered_unique_urls": 113,
      "still_failed_unique_urls": 139
    },
    "elapsed_seconds": 424.9
  },
  "coverage": {
    "minimum_unique_urls_per_important_channel": 1,
    "min_sources_per_important_name": 1,
    "fail_on_missing_cctv": true,
    "fail_on_missing_satellite": true,
    "required_cctv": [
      {
        "name": "CCTV-1",
        "published_rows": 6,
        "unique_urls": 6,
        "count": 6
      },
      {
        "name": "CCTV-2",
        "published_rows": 6,
        "unique_urls": 6,
        "count": 6
      },
      {
        "name": "CCTV-3",
        "published_rows": 6,
        "unique_urls": 6,
        "count": 6
      },
      {
        "name": "CCTV-4",
        "published_rows": 6,
        "unique_urls": 6,
        "count": 6
      },
      {
        "name": "CCTV-5",
        "published_rows": 6,
        "unique_urls": 6,
        "count": 6
      },
      {
        "name": "CCTV-6",
        "published_rows": 6,
        "unique_urls": 6,
        "count": 6
      },
      {
        "name": "CCTV-7",
        "published_rows": 6,
        "unique_urls": 6,
        "count": 6
      },
      {
        "name": "CCTV-8",
        "published_rows": 6,
        "unique_urls": 6,
        "count": 6
      },
      {
        "name": "CCTV-9",
        "published_rows": 6,
        "unique_urls": 6,
        "count": 6
      },
      {
        "name": "CCTV-10",
        "published_rows": 6,
        "unique_urls": 6,
        "count": 6
      },
      {
        "name": "CCTV-11",
        "published_rows": 6,
        "unique_urls": 6,
        "count": 6
      },
      {
        "name": "CCTV-12",
        "published_rows": 6,
        "unique_urls": 6,
        "count": 6
      },
      {
        "name": "CCTV-13",
        "published_rows": 6,
        "unique_urls": 6,
        "count": 6
      },
      {
        "name": "CCTV-14",
        "published_rows": 6,
        "unique_urls": 6,
        "count": 6
      },
      {
        "name": "CCTV-15",
        "published_rows": 6,
        "unique_urls": 6,
        "count": 6
      },
      {
        "name": "CCTV-16",
        "published_rows": 5,
        "unique_urls": 5,
        "count": 5
      },
      {
        "name": "CCTV-17",
        "published_rows": 6,
        "unique_urls": 6,
        "count": 6
      },
      {
        "name": "CCTV-5+",
        "published_rows": 4,
        "unique_urls": 4,
        "count": 4
      }
    ],
    "required_cctv_variants": [
      {
        "name": "CCTV-1",
        "published_rows": 1,
        "unique_urls": 1,
        "variant_count": 1
      },
      {
        "name": "CCTV-4",
        "published_rows": 6,
        "unique_urls": 6,
        "variant_count": 6
      },
      {
        "name": "CCTV-5",
        "published_rows": 5,
        "unique_urls": 5,
        "variant_count": 5
      },
      {
        "name": "CCTV-8",
        "published_rows": 6,
        "unique_urls": 6,
        "variant_count": 6
      },
      {
        "name": "CCTV-11",
        "published_rows": 1,
        "unique_urls": 1,
        "variant_count": 1
      },
      {
        "name": "CCTV-12",
        "published_rows": 1,
        "unique_urls": 1,
        "variant_count": 1
      },
      {
        "name": "CCTV-5+",
        "published_rows": 4,
        "unique_urls": 4,
        "variant_count": 4
      }
    ],
    "important_satellite": [
      {
        "name": "辽宁卫视",
        "published_rows": 6,
        "unique_urls": 6,
        "count": 6
      },
      {
        "name": "河北卫视",
        "published_rows": 6,
        "unique_urls": 6,
        "count": 6
      },
      {
        "name": "河南卫视",
        "published_rows": 6,
        "unique_urls": 6,
        "count": 6
      },
      {
        "name": "北京卫视",
        "published_rows": 6,
        "unique_urls": 6,
        "count": 6
      },
      {
        "name": "东方卫视",
        "published_rows": 6,
        "unique_urls": 6,
        "count": 6
      },
      {
        "name": "浙江卫视",
        "published_rows": 6,
        "unique_urls": 6,
        "count": 6
      },
      {
        "name": "江苏卫视",
        "published_rows": 6,
        "unique_urls": 6,
        "count": 6
      },
      {
        "name": "湖南卫视",
        "published_rows": 6,
        "unique_urls": 6,
        "count": 6
      },
      {
        "name": "广东卫视",
        "published_rows": 6,
        "unique_urls": 6,
        "count": 6
      },
      {
        "name": "深圳卫视",
        "published_rows": 6,
        "unique_urls": 6,
        "count": 6
      }
    ],
    "missing_cctv": [],
    "missing_satellite": []
  },
  "quality_audit": {
    "status": "ok",
    "rows": 2661,
    "unique_channel_identities": 1633,
    "unique_names": 1633,
    "unique_urls": 2661,
    "groups": {
      "央视频道": 129,
      "卫视频道": 182,
      "地方频道": 827,
      "影视剧场": 172,
      "少儿动漫": 25,
      "体育纪实": 64,
      "音乐综艺": 24,
      "生活休闲": 89,
      "综合娱乐": 868,
      "港澳台频道": 64,
      "海外华语频道": 217
    },
    "min_exact_cctv_unique_urls": 3,
    "min_important_satellite_unique_urls": 3,
    "required_cctv": [
      {
        "name": "CCTV-1",
        "published_rows": 6,
        "unique_urls": 6,
        "count": 6
      },
      {
        "name": "CCTV-2",
        "published_rows": 6,
        "unique_urls": 6,
        "count": 6
      },
      {
        "name": "CCTV-3",
        "published_rows": 6,
        "unique_urls": 6,
        "count": 6
      },
      {
        "name": "CCTV-4",
        "published_rows": 6,
        "unique_urls": 6,
        "count": 6
      },
      {
        "name": "CCTV-5",
        "published_rows": 6,
        "unique_urls": 6,
        "count": 6
      },
      {
        "name": "CCTV-6",
        "published_rows": 6,
        "unique_urls": 6,
        "count": 6
      },
      {
        "name": "CCTV-7",
        "published_rows": 6,
        "unique_urls": 6,
        "count": 6
      },
      {
        "name": "CCTV-8",
        "published_rows": 6,
        "unique_urls": 6,
        "count": 6
      },
      {
        "name": "CCTV-9",
        "published_rows": 6,
        "unique_urls": 6,
        "count": 6
      },
      {
        "name": "CCTV-10",
        "published_rows": 6,
        "unique_urls": 6,
        "count": 6
      },
      {
        "name": "CCTV-11",
        "published_rows": 6,
        "unique_urls": 6,
        "count": 6
      },
      {
        "name": "CCTV-12",
        "published_rows": 6,
        "unique_urls": 6,
        "count": 6
      },
      {
        "name": "CCTV-13",
        "published_rows": 6,
        "unique_urls": 6,
        "count": 6
      },
      {
        "name": "CCTV-14",
        "published_rows": 6,
        "unique_urls": 6,
        "count": 6
      },
      {
        "name": "CCTV-15",
        "published_rows": 6,
        "unique_urls": 6,
        "count": 6
      },
      {
        "name": "CCTV-16",
        "published_rows": 5,
        "unique_urls": 5,
        "count": 5
      },
      {
        "name": "CCTV-17",
        "published_rows": 6,
        "unique_urls": 6,
        "count": 6
      },
      {
        "name": "CCTV-5+",
        "published_rows": 4,
        "unique_urls": 4,
        "count": 4
      }
    ],
    "important_satellite": [
      {
        "name": "辽宁卫视",
        "published_rows": 6,
        "unique_urls": 6,
        "count": 6
      },
      {
        "name": "河北卫视",
        "published_rows": 6,
        "unique_urls": 6,
        "count": 6
      },
      {
        "name": "河南卫视",
        "published_rows": 6,
        "unique_urls": 6,
        "count": 6
      },
      {
        "name": "北京卫视",
        "published_rows": 6,
        "unique_urls": 6,
        "count": 6
      },
      {
        "name": "东方卫视",
        "published_rows": 6,
        "unique_urls": 6,
        "count": 6
      },
      {
        "name": "浙江卫视",
        "published_rows": 6,
        "unique_urls": 6,
        "count": 6
      },
      {
        "name": "江苏卫视",
        "published_rows": 6,
        "unique_urls": 6,
        "count": 6
      },
      {
        "name": "湖南卫视",
        "published_rows": 6,
        "unique_urls": 6,
        "count": 6
      },
      {
        "name": "广东卫视",
        "published_rows": 6,
        "unique_urls": 6,
        "count": 6
      },
      {
        "name": "深圳卫视",
        "published_rows": 6,
        "unique_urls": 6,
        "count": 6
      }
    ],
    "missing_cctv_quality": [],
    "missing_satellite_quality": [],
    "weak_cctv": [],
    "weak_satellite": [],
    "strict_filter_residue": [],
    "strict_filter_residue_count": 0,
    "latin_noise_review_count": 4,
    "latin_noise_review_sample": [
      {
        "group": "音乐综艺",
        "name": "音乐_AT_KroneHit",
        "url": "http://bitcdn-kronehit.bitmovin.com/v2/hls/master.m3u8"
      },
      {
        "group": "港澳台频道",
        "name": "ELEVEN体育1",
        "url": "https://stream1.freetv.fun/eltaai-er-da-ti-yu--1--wj-1.ctv"
      },
      {
        "group": "港澳台频道",
        "name": "ELEVEN体育2",
        "url": "https://stream1.freetv.fun/eltaai-er-da-ti-yu--2--wj-1.ctv"
      },
      {
        "group": "港澳台频道",
        "name": "ELEVEN体育3",
        "url": "https://stream1.freetv.fun/eltaai-er-da-ti-yu--3--wj-1.ctv"
      }
    ],
    "channel_limit_violations": [],
    "channel_limit_violation_count": 0,
    "group_limit_violations": [],
    "identity_group_conflicts": [],
    "identity_group_conflict_count": 0,
    "url_identity_conflicts": [],
    "url_identity_conflict_count": 0,
    "failures": [],
    "warnings": [
      "latin/noise-like channel names remain for review: 4"
    ]
  },
  "family_quality_audit": {
    "status": "ok",
    "rows": 1169,
    "unique_names": 891,
    "unique_channel_identities": 891,
    "unique_urls": 1169,
    "groups": {
      "央视频道": 91,
      "卫视频道": 144,
      "地方频道": 320,
      "影视剧场": 90,
      "少儿动漫": 14,
      "体育纪实": 43,
      "音乐综艺": 20,
      "生活休闲": 57,
      "综合娱乐": 260,
      "港澳台频道": 50,
      "海外华语频道": 80
    },
    "required_cctv": [
      {
        "name": "CCTV-1",
        "published_rows": 4,
        "unique_urls": 4,
        "count": 4
      },
      {
        "name": "CCTV-2",
        "published_rows": 4,
        "unique_urls": 4,
        "count": 4
      },
      {
        "name": "CCTV-3",
        "published_rows": 4,
        "unique_urls": 4,
        "count": 4
      },
      {
        "name": "CCTV-4",
        "published_rows": 4,
        "unique_urls": 4,
        "count": 4
      },
      {
        "name": "CCTV-5",
        "published_rows": 4,
        "unique_urls": 4,
        "count": 4
      },
      {
        "name": "CCTV-6",
        "published_rows": 4,
        "unique_urls": 4,
        "count": 4
      },
      {
        "name": "CCTV-7",
        "published_rows": 4,
        "unique_urls": 4,
        "count": 4
      },
      {
        "name": "CCTV-8",
        "published_rows": 4,
        "unique_urls": 4,
        "count": 4
      },
      {
        "name": "CCTV-9",
        "published_rows": 4,
        "unique_urls": 4,
        "count": 4
      },
      {
        "name": "CCTV-10",
        "published_rows": 4,
        "unique_urls": 4,
        "count": 4
      },
      {
        "name": "CCTV-11",
        "published_rows": 4,
        "unique_urls": 4,
        "count": 4
      },
      {
        "name": "CCTV-12",
        "published_rows": 4,
        "unique_urls": 4,
        "count": 4
      },
      {
        "name": "CCTV-13",
        "published_rows": 4,
        "unique_urls": 4,
        "count": 4
      },
      {
        "name": "CCTV-14",
        "published_rows": 4,
        "unique_urls": 4,
        "count": 4
      },
      {
        "name": "CCTV-15",
        "published_rows": 4,
        "unique_urls": 4,
        "count": 4
      },
      {
        "name": "CCTV-16",
        "published_rows": 4,
        "unique_urls": 4,
        "count": 4
      },
      {
        "name": "CCTV-17",
        "published_rows": 4,
        "unique_urls": 4,
        "count": 4
      },
      {
        "name": "CCTV-5+",
        "published_rows": 4,
        "unique_urls": 4,
        "count": 4
      }
    ],
    "important_satellite": [
      {
        "name": "辽宁卫视",
        "published_rows": 4,
        "unique_urls": 4,
        "count": 4
      },
      {
        "name": "河北卫视",
        "published_rows": 4,
        "unique_urls": 4,
        "count": 4
      },
      {
        "name": "河南卫视",
        "published_rows": 4,
        "unique_urls": 4,
        "count": 4
      },
      {
        "name": "北京卫视",
        "published_rows": 4,
        "unique_urls": 4,
        "count": 4
      },
      {
        "name": "东方卫视",
        "published_rows": 4,
        "unique_urls": 4,
        "count": 4
      },
      {
        "name": "浙江卫视",
        "published_rows": 4,
        "unique_urls": 4,
        "count": 4
      },
      {
        "name": "江苏卫视",
        "published_rows": 4,
        "unique_urls": 4,
        "count": 4
      },
      {
        "name": "湖南卫视",
        "published_rows": 4,
        "unique_urls": 4,
        "count": 4
      },
      {
        "name": "广东卫视",
        "published_rows": 4,
        "unique_urls": 4,
        "count": 4
      },
      {
        "name": "深圳卫视",
        "published_rows": 4,
        "unique_urls": 4,
        "count": 4
      }
    ],
    "min_exact_cctv_unique_urls": 3,
    "min_important_satellite_unique_urls": 3,
    "missing_cctv_quality": [],
    "missing_satellite_quality": [],
    "group_limit_violations": [],
    "per_identity_limit_violations": [],
    "failures": []
  },
  "publish_guard": {
    "schema_version": 2,
    "status": "ok",
    "baseline_lines": 2609,
    "current_lines": 2661,
    "total_drop_ratio": -0.019931008049060943,
    "min_lines": 1800,
    "max_total_drop_ratio": 0.2,
    "max_failed_sources": 5,
    "core_failed_fail_threshold": 2,
    "core_sources": [
      "bigbiggrandg_gather",
      "epg_cn",
      "guovin_ipv4",
      "iyouhun_zb",
      "suxuang_ipv4",
      "zbds_iptv4_txt"
    ],
    "group_deltas": {
      "央视频道": {
        "baseline": 132,
        "current": 129,
        "delta": -3,
        "drop_ratio": 0.022727272727272728
      },
      "卫视频道": {
        "baseline": 183,
        "current": 182,
        "delta": -1,
        "drop_ratio": 0.00546448087431694
      },
      "地方频道": {
        "baseline": 787,
        "current": 827,
        "delta": 40,
        "drop_ratio": -0.05082592121982211
      },
      "影视剧场": {
        "baseline": 173,
        "current": 172,
        "delta": -1,
        "drop_ratio": 0.005780346820809248
      },
      "少儿动漫": {
        "baseline": 28,
        "current": 25,
        "delta": -3,
        "drop_ratio": 0.10714285714285714
      },
      "体育纪实": {
        "baseline": 66,
        "current": 64,
        "delta": -2,
        "drop_ratio": 0.030303030303030304
      },
      "音乐综艺": {
        "baseline": 24,
        "current": 24,
        "delta": 0,
        "drop_ratio": 0.0
      },
      "生活休闲": {
        "baseline": 75,
        "current": 89,
        "delta": 14,
        "drop_ratio": -0.18666666666666668
      },
      "综合娱乐": {
        "baseline": 864,
        "current": 868,
        "delta": 4,
        "drop_ratio": -0.004629629629629629
      },
      "港澳台频道": {
        "baseline": 64,
        "current": 64,
        "delta": 0,
        "drop_ratio": 0.0
      },
      "海外华语频道": {
        "baseline": 213,
        "current": 217,
        "delta": 4,
        "drop_ratio": -0.018779342723004695
      }
    },
    "failed_sources": [],
    "zero_parsed_sources": [],
    "failures": [],
    "warnings": []
  },
  "publish_size": {
    "status": "ok",
    "measurement_scope": "publication payload files; self-referential control files are verified by publish-manifest.json",
    "excluded_control_files": [
      "full-check-summary.json",
      "publish-size-report.md",
      "publish-manifest.json"
    ],
    "manifest_file": "publish-manifest.json",
    "files": {
      "live-curated.txt": 223596,
      "live.txt": 223596,
      "live-verified.txt": 223596,
      "ku9-live.txt": 223596,
      "live.m3u": 399986,
      "ku9-family.txt": 98168,
      "live-family.txt": 98168,
      "family.m3u": 177190,
      "stability-history.tsv": 744727,
      "final-publish-report.md": 11697,
      "stability-report.md": 10519,
      "coverage-report.md": 1350,
      "quality-audit-report.md": 1435,
      "publish-guard-report.md": 789,
      "published-recheck-report.md": 27555,
      "source-report.md": 5866,
      "check-report.md": 5866,
      "curated-report.md": 3591,
      "sources_status.csv": 2603
    },
    "txt_alias_same_hash": true,
    "family_txt_alias_same_hash": true,
    "txt_alias_hashes": {
      "live-curated.txt": "db43eca6e7d1f0e406a5e432c7be0c4205b9fa94b9e3880729743b34577b5c91",
      "live.txt": "db43eca6e7d1f0e406a5e432c7be0c4205b9fa94b9e3880729743b34577b5c91",
      "live-verified.txt": "db43eca6e7d1f0e406a5e432c7be0c4205b9fa94b9e3880729743b34577b5c91",
      "ku9-live.txt": "db43eca6e7d1f0e406a5e432c7be0c4205b9fa94b9e3880729743b34577b5c91"
    },
    "family_txt_alias_hashes": {
      "ku9-family.txt": "5f3eee73851c22cd5fdbd8fcc58cf00e755e6ff733fdd8bb542fdbdaa07a5b4c",
      "live-family.txt": "5f3eee73851c22cd5fdbd8fcc58cf00e755e6ff733fdd8bb542fdbdaa07a5b4c"
    },
    "working_tree_payload_bytes": 2483894,
    "unique_payload_blob_bytes": 1709072,
    "duplicate_txt_worktree_bytes": 670788,
    "max_unique_payload_blob_bytes": 2500000,
    "forbidden_tracked_artifacts": [],
    "failures": [],
    "warnings": [
      "TXT aliases occupy duplicate working-tree bytes for compatibility, but Git stores their identical content as one blob."
    ]
  }
}
